sozipfile/__init__.py
sozipfile/sozipfile.py
sozipfile-0.3.2.dist-info/LICENSE
sozipfile-0.3.2.dist-info/METADATA
sozipfile-0.3.2.dist-info/WHEEL
sozipfile-0.3.2.dist-info/top_level.txt
sozipfile-0.3.2.dist-info/RECORD
