Metadata-Version: 2.1
Name: sozipfile
Version: 0.3.2
Summary: Fork of Python zipfile module, adding generation of sozip optimization
Author-email: "Even Rouault (using code from Python contributors)" <even.rouault@spatialys.com>
Project-URL: Homepage, https://github.com/sozip/sozipfile
Project-URL: Bug Tracker, https://github.com/sozip/sozipfile/issues
Classifier: Programming Language :: Python :: 3
Classifier: License :: OSI Approved :: Python Software Foundation License
Classifier: Operating System :: OS Independent
Requires-Python: >=3.8
License-File: LICENSE
